astraszab_hypermodern_python/.readthedocs.yml
astraszab_hypermodern_python/__init__.py
astraszab_hypermodern_python/console.py
astraszab_hypermodern_python/wikipedia.py
astraszab_hypermodern_python-0.1.1.dist-info/entry_points.txt
astraszab_hypermodern_python-0.1.1.dist-info/LICENSE
astraszab_hypermodern_python-0.1.1.dist-info/WHEEL
astraszab_hypermodern_python-0.1.1.dist-info/METADATA
astraszab_hypermodern_python-0.1.1.dist-info/RECORD
